calDB/__init__.py
calDB/calCode.py
calDB-0.1.4.dist-info/LICENSE
calDB-0.1.4.dist-info/METADATA
calDB-0.1.4.dist-info/WHEEL
calDB-0.1.4.dist-info/top_level.txt
calDB-0.1.4.dist-info/RECORD
