Metadata-Version: 2.1
Name: calDB
Version: 0.1.4
Summary: Makes it easy for users to interact with cal++ in python.
Home-page: UNKNOWN
Author: Jaden Ong
Author-email: jadenweong@gmail.com
License: UNKNOWN
Platform: UNKNOWN
Classifier: Programming Language :: Python :: 3
Classifier: License :: OSI Approved :: MIT License
Classifier: Operating System :: OS Independent
Requires-Python: >=3.8
License-File: LICENSE
